Workbook

Sheet Instruções
B1: Artur Vasconcelos – Tecnologia e Dados
B2: Levantamento de tarefas para automação
B3: Preparado para Amparo Assis Contábil
B5: Para que serve
B6: • | C6: Este formulário é o primeiro passo do projeto de automação. Com ele, entendo como cada tarefa é feita hoje e quais têm mais potencial para serem automatizadas.
B8: Como preencher
B9: • | C9: Use uma aba para cada tarefa: Tarefa 1, Tarefa 2 e assim por diante.
B10: • | C10: Precisa de mais abas? Clique com o botão direito em uma aba de tarefa > Mover ou copiar > marque "Criar uma cópia".
B11: • | C11: Preencha só as células amarelas. As azuis são calculadas sozinhas.
B12: • | C12: Nos campos com seta, escolha uma opção da lista.
B13: • | C13: Descreva como explicaria para alguém novo no escritório. Não precisa de termos técnicos.
B14: • | C14: Estimativas de tempo bastam: "mais ou menos 30 minutos" já ajuda muito.
B15: • | C15: Não precisa preencher tudo. Um campo vazio é melhor que um chute.
B16: • | C16: Veja a aba Exemplo para um modelo preenchido.
B18: Importante: dados de clientes
B19: • | C19: Não coloquem dados reais de clientes ou funcionários (nomes, CPF, valores). Descrevam só o tipo de documento ou informação.
B21: Depois de preencher
B22: • | C22: Salvem o arquivo e devolvam por e-mail para artur.augustocv@gmail.com.
B23: • | C23: A aba Resumo mostra todas as tarefas juntas e o total de horas por mês.
B24: • | C24: Entro em contato para conversarmos sobre as tarefas e apresentar a análise.
B26: Legenda
C27: Célula para preencher
C28: Calculado automaticamente
B30: Dúvidas
C31: Artur Vasconcelos · WhatsApp (11) 9-4114-4850 · artur.augustocv@gmail.com

Sheet Exemplo
B1: Artur Vasconcelos – Tecnologia e Dados
B2: Exemplo preenchido
B3: Tarefa fictícia, só para mostrar como preencher
B5: 1. Identificação
B6: Nome da tarefa | C6: Organizar documentos recebidos dos clientes por e-mail | D6: Um nome curto. Ex.: Organizar documentos recebidos por e-mail
B7: Quem faz hoje | C7: Recepção / atendimento | D7: Função ou setor (não precisa de nome). Ex.: Departamento pessoal
B8: Quantas pessoas fazem essa tarefa | C8: 2 | D8: Número aproximado
B10: 2. Como é feita hoje
B11: Passo a passo | C11: 1. Abrir a caixa de e-mail do escritório. 2. Baixar os anexos de cada cliente. 3. Renomear no padrão: CLIENTE - TIPO - MÊS. 4. Salvar na pasta do cliente no servidor. 5. Avisar o responsável pelo cliente que o documento chegou. | D11: Descreva como explicaria para alguém novo no escritório. Pode usar frases curtas, uma por etapa.
B12: O que dá início à tarefa | C12: Chegada de e-mail de cliente com anexo | D12: Ex.: chega um e-mail, começa o mês, o cliente pede, vence um prazo
B13: Sistemas e programas usados | C13: E-mail, pastas do servidor | D13: Ex.: sistema da folha, Excel, e-mail, site da Receita ou da prefeitura
B14: Documentos e arquivos usados | C14: PDF de notas fiscais, extratos e guias; às vezes foto do celular | D14: Só o tipo, sem dados reais. Ex.: PDF de nota fiscal, planilha do cliente, papel
B15: Resultado final | C15: Documento salvo na pasta certa e responsável avisado | D15: O que é entregue ao final e para quem
B17: 3. Tempo e frequência
B18: Com que frequência acontece | C18: Diária | D18: Escolha na lista
B19: Quantas vezes por mês, aproximadamente | C19: 22 | D19: Ex.: diária ≈ 22 · semanal ≈ 4 · mensal = 1
B20: Tempo gasto em cada vez (minutos) | C20: 30 | D20: Uma estimativa já basta
B21: Horas por mês gastas hoje | C21: =IF(OR(C19="",C20=""),"",C19*C20/60) | D21: Calculado automaticamente
B22: Tem prazo ou época de pico? | C22: Aumenta muito nos primeiros 10 dias do mês | D22: Ex.: sempre até o dia 20; aumenta no fim do ano
B24: 4. Dificuldades
B25: Onde costuma dar erro ou retrabalho | C25: Arquivo salvo na pasta errada ou com nome fora do padrão; e-mail esquecido | D25: O que mais incomoda nessa tarefa
B26: A tarefa segue regras fixas ou exige decisão? | C26: Sempre as mesmas regras | D26: Escolha na lista
B27: Envolve dados pessoais? (CPF, salário, dados de funcionários de clientes) | C27: Sim | D27: Escolha na lista
B29: 5. Expectativa
B30: Como imaginam essa tarefa automatizada | C30: Os anexos já chegarem renomeados na pasta do cliente, com um aviso para o responsável | D30: Não precisa ser técnico. Ex.: os arquivos já chegarem organizados na pasta do cliente
B31: Quantas horas por mês esperam economizar | C31: 10 | D31: Uma estimativa
B32: Importância para o escritório | C32: Alta | D32: Escolha na lista
B33: Observações | C33: Exemplo fictício, só para mostrar como preencher. | D33: Qualquer detalhe que ajude a entender

Sheet Tarefa 1
B1: Artur Vasconcelos – Tecnologia e Dados
B2: Tarefa 1
B3: Preencha as células amarelas
B5: 1. Identificação
B6: Nome da tarefa | D6: Um nome curto. Ex.: Organizar documentos recebidos por e-mail
B7: Quem faz hoje | D7: Função ou setor (não precisa de nome). Ex.: Departamento pessoal
B8: Quantas pessoas fazem essa tarefa | D8: Número aproximado
B10: 2. Como é feita hoje
B11: Passo a passo | D11: Descreva como explicaria para alguém novo no escritório. Pode usar frases curtas, uma por etapa.
B12: O que dá início à tarefa | D12: Ex.: chega um e-mail, começa o mês, o cliente pede, vence um prazo
B13: Sistemas e programas usados | D13: Ex.: sistema da folha, Excel, e-mail, site da Receita ou da prefeitura
B14: Documentos e arquivos usados | D14: Só o tipo, sem dados reais. Ex.: PDF de nota fiscal, planilha do cliente, papel
B15: Resultado final | D15: O que é entregue ao final e para quem
B17: 3. Tempo e frequência
B18: Com que frequência acontece | D18: Escolha na lista
B19: Quantas vezes por mês, aproximadamente | D19: Ex.: diária ≈ 22 · semanal ≈ 4 · mensal = 1
B20: Tempo gasto em cada vez (minutos) | D20: Uma estimativa já basta
B21: Horas por mês gastas hoje | C21: =IF(OR(C19="",C20=""),"",C19*C20/60) | D21: Calculado automaticamente
B22: Tem prazo ou época de pico? | D22: Ex.: sempre até o dia 20; aumenta no fim do ano
B24: 4. Dificuldades
B25: Onde costuma dar erro ou retrabalho | D25: O que mais incomoda nessa tarefa
B26: A tarefa segue regras fixas ou exige decisão? | D26: Escolha na lista
B27: Envolve dados pessoais? (CPF, salário, dados de funcionários de clientes) | D27: Escolha na lista
B29: 5. Expectativa
B30: Como imaginam essa tarefa automatizada | D30: Não precisa ser técnico. Ex.: os arquivos já chegarem organizados na pasta do cliente
B31: Quantas horas por mês esperam economizar | D31: Uma estimativa
B32: Importância para o escritório | D32: Escolha na lista
B33: Observações | D33: Qualquer detalhe que ajude a entender

Sheet Tarefa 2
B1: Artur Vasconcelos – Tecnologia e Dados
B2: Tarefa 2
B3: Preencha as células amarelas
B5: 1. Identificação
B6: Nome da tarefa | D6: Um nome curto. Ex.: Organizar documentos recebidos por e-mail
B7: Quem faz hoje | D7: Função ou setor (não precisa de nome). Ex.: Departamento pessoal
B8: Quantas pessoas fazem essa tarefa | D8: Número aproximado
B10: 2. Como é feita hoje
B11: Passo a passo | D11: Descreva como explicaria para alguém novo no escritório. Pode usar frases curtas, uma por etapa.
B12: O que dá início à tarefa | D12: Ex.: chega um e-mail, começa o mês, o cliente pede, vence um prazo
B13: Sistemas e programas usados | D13: Ex.: sistema da folha, Excel, e-mail, site da Receita ou da prefeitura
B14: Documentos e arquivos usados | D14: Só o tipo, sem dados reais. Ex.: PDF de nota fiscal, planilha do cliente, papel
B15: Resultado final | D15: O que é entregue ao final e para quem
B17: 3. Tempo e frequência
B18: Com que frequência acontece | D18: Escolha na lista
B19: Quantas vezes por mês, aproximadamente | D19: Ex.: diária ≈ 22 · semanal ≈ 4 · mensal = 1
B20: Tempo gasto em cada vez (minutos) | D20: Uma estimativa já basta
B21: Horas por mês gastas hoje | C21: =IF(OR(C19="",C20=""),"",C19*C20/60) | D21: Calculado automaticamente
B22: Tem prazo ou época de pico? | D22: Ex.: sempre até o dia 20; aumenta no fim do ano
B24: 4. Dificuldades
B25: Onde costuma dar erro ou retrabalho | D25: O que mais incomoda nessa tarefa
B26: A tarefa segue regras fixas ou exige decisão? | D26: Escolha na lista
B27: Envolve dados pessoais? (CPF, salário, dados de funcionários de clientes) | D27: Escolha na lista
B29: 5. Expectativa
B30: Como imaginam essa tarefa automatizada | D30: Não precisa ser técnico. Ex.: os arquivos já chegarem organizados na pasta do cliente
B31: Quantas horas por mês esperam economizar | D31: Uma estimativa
B32: Importância para o escritório | D32: Escolha na lista
B33: Observações | D33: Qualquer detalhe que ajude a entender

Sheet Tarefa 3
B1: Artur Vasconcelos – Tecnologia e Dados
B2: Tarefa 3
B3: Preencha as células amarelas
B5: 1. Identificação
B6: Nome da tarefa | D6: Um nome curto. Ex.: Organizar documentos recebidos por e-mail
B7: Quem faz hoje | D7: Função ou setor (não precisa de nome). Ex.: Departamento pessoal
B8: Quantas pessoas fazem essa tarefa | D8: Número aproximado
B10: 2. Como é feita hoje
B11: Passo a passo | D11: Descreva como explicaria para alguém novo no escritório. Pode usar frases curtas, uma por etapa.
B12: O que dá início à tarefa | D12: Ex.: chega um e-mail, começa o mês, o cliente pede, vence um prazo
B13: Sistemas e programas usados | D13: Ex.: sistema da folha, Excel, e-mail, site da Receita ou da prefeitura
B14: Documentos e arquivos usados | D14: Só o tipo, sem dados reais. Ex.: PDF de nota fiscal, planilha do cliente, papel
B15: Resultado final | D15: O que é entregue ao final e para quem
B17: 3. Tempo e frequência
B18: Com que frequência acontece | D18: Escolha na lista
B19: Quantas vezes por mês, aproximadamente | D19: Ex.: diária ≈ 22 · semanal ≈ 4 · mensal = 1
B20: Tempo gasto em cada vez (minutos) | D20: Uma estimativa já basta
B21: Horas por mês gastas hoje | C21: =IF(OR(C19="",C20=""),"",C19*C20/60) | D21: Calculado automaticamente
B22: Tem prazo ou época de pico? | D22: Ex.: sempre até o dia 20; aumenta no fim do ano
B24: 4. Dificuldades
B25: Onde costuma dar erro ou retrabalho | D25: O que mais incomoda nessa tarefa
B26: A tarefa segue regras fixas ou exige decisão? | D26: Escolha na lista
B27: Envolve dados pessoais? (CPF, salário, dados de funcionários de clientes) | D27: Escolha na lista
B29: 5. Expectativa
B30: Como imaginam essa tarefa automatizada | D30: Não precisa ser técnico. Ex.: os arquivos já chegarem organizados na pasta do cliente
B31: Quantas horas por mês esperam economizar | D31: Uma estimativa
B32: Importância para o escritório | D32: Escolha na lista
B33: Observações | D33: Qualquer detalhe que ajude a entender

Sheet Tarefa 4
B1: Artur Vasconcelos – Tecnologia e Dados
B2: Tarefa 4
B3: Preencha as células amarelas
B5: 1. Identificação
B6: Nome da tarefa | D6: Um nome curto. Ex.: Organizar documentos recebidos por e-mail
B7: Quem faz hoje | D7: Função ou setor (não precisa de nome). Ex.: Departamento pessoal
B8: Quantas pessoas fazem essa tarefa | D8: Número aproximado
B10: 2. Como é feita hoje
B11: Passo a passo | D11: Descreva como explicaria para alguém novo no escritório. Pode usar frases curtas, uma por etapa.
B12: O que dá início à tarefa | D12: Ex.: chega um e-mail, começa o mês, o cliente pede, vence um prazo
B13: Sistemas e programas usados | D13: Ex.: sistema da folha, Excel, e-mail, site da Receita ou da prefeitura
B14: Documentos e arquivos usados | D14: Só o tipo, sem dados reais. Ex.: PDF de nota fiscal, planilha do cliente, papel
B15: Resultado final | D15: O que é entregue ao final e para quem
B17: 3. Tempo e frequência
B18: Com que frequência acontece | D18: Escolha na lista
B19: Quantas vezes por mês, aproximadamente | D19: Ex.: diária ≈ 22 · semanal ≈ 4 · mensal = 1
B20: Tempo gasto em cada vez (minutos) | D20: Uma estimativa já basta
B21: Horas por mês gastas hoje | C21: =IF(OR(C19="",C20=""),"",C19*C20/60) | D21: Calculado automaticamente
B22: Tem prazo ou época de pico? | D22: Ex.: sempre até o dia 20; aumenta no fim do ano
B24: 4. Dificuldades
B25: Onde costuma dar erro ou retrabalho | D25: O que mais incomoda nessa tarefa
B26: A tarefa segue regras fixas ou exige decisão? | D26: Escolha na lista
B27: Envolve dados pessoais? (CPF, salário, dados de funcionários de clientes) | D27: Escolha na lista
B29: 5. Expectativa
B30: Como imaginam essa tarefa automatizada | D30: Não precisa ser técnico. Ex.: os arquivos já chegarem organizados na pasta do cliente
B31: Quantas horas por mês esperam economizar | D31: Uma estimativa
B32: Importância para o escritório | D32: Escolha na lista
B33: Observações | D33: Qualquer detalhe que ajude a entender

Sheet Tarefa 5
B1: Artur Vasconcelos – Tecnologia e Dados
B2: Tarefa 5
B3: Preencha as células amarelas
B5: 1. Identificação
B6: Nome da tarefa | D6: Um nome curto. Ex.: Organizar documentos recebidos por e-mail
B7: Quem faz hoje | D7: Função ou setor (não precisa de nome). Ex.: Departamento pessoal
B8: Quantas pessoas fazem essa tarefa | D8: Número aproximado
B10: 2. Como é feita hoje
B11: Passo a passo | D11: Descreva como explicaria para alguém novo no escritório. Pode usar frases curtas, uma por etapa.
B12: O que dá início à tarefa | D12: Ex.: chega um e-mail, começa o mês, o cliente pede, vence um prazo
B13: Sistemas e programas usados | D13: Ex.: sistema da folha, Excel, e-mail, site da Receita ou da prefeitura
B14: Documentos e arquivos usados | D14: Só o tipo, sem dados reais. Ex.: PDF de nota fiscal, planilha do cliente, papel
B15: Resultado final | D15: O que é entregue ao final e para quem
B17: 3. Tempo e frequência
B18: Com que frequência acontece | D18: Escolha na lista
B19: Quantas vezes por mês, aproximadamente | D19: Ex.: diária ≈ 22 · semanal ≈ 4 · mensal = 1
B20: Tempo gasto em cada vez (minutos) | D20: Uma estimativa já basta
B21: Horas por mês gastas hoje | C21: =IF(OR(C19="",C20=""),"",C19*C20/60) | D21: Calculado automaticamente
B22: Tem prazo ou época de pico? | D22: Ex.: sempre até o dia 20; aumenta no fim do ano
B24: 4. Dificuldades
B25: Onde costuma dar erro ou retrabalho | D25: O que mais incomoda nessa tarefa
B26: A tarefa segue regras fixas ou exige decisão? | D26: Escolha na lista
B27: Envolve dados pessoais? (CPF, salário, dados de funcionários de clientes) | D27: Escolha na lista
B29: 5. Expectativa
B30: Como imaginam essa tarefa automatizada | D30: Não precisa ser técnico. Ex.: os arquivos já chegarem organizados na pasta do cliente
B31: Quantas horas por mês esperam economizar | D31: Uma estimativa
B32: Importância para o escritório | D32: Escolha na lista
B33: Observações | D33: Qualquer detalhe que ajude a entender

Sheet Resumo
B1: Artur Vasconcelos – Tecnologia e Dados
B2: Resumo das tarefas
B3: Preenchido automaticamente a partir das abas de tarefa
B5: Tarefa | C5: Frequência | D5: Horas/mês hoje | E5: Economia esperada (h/mês) | F5: Importância | G5: Dados pessoais?
B6: =IF('Tarefa 1'!C6="","",'Tarefa 1'!C6) | C6: =IF('Tarefa 1'!C18="","",'Tarefa 1'!C18) | D6: =IF('Tarefa 1'!C21="","",'Tarefa 1'!C21) | E6: =IF('Tarefa 1'!C31="","",'Tarefa 1'!C31) | F6: =IF('Tarefa 1'!C32="","",'Tarefa 1'!C32) | G6: =IF('Tarefa 1'!C27="","",'Tarefa 1'!C27)
B7: =IF('Tarefa 2'!C6="","",'Tarefa 2'!C6) | C7: =IF('Tarefa 2'!C18="","",'Tarefa 2'!C18) | D7: =IF('Tarefa 2'!C21="","",'Tarefa 2'!C21) | E7: =IF('Tarefa 2'!C31="","",'Tarefa 2'!C31) | F7: =IF('Tarefa 2'!C32="","",'Tarefa 2'!C32) | G7: =IF('Tarefa 2'!C27="","",'Tarefa 2'!C27)
B8: =IF('Tarefa 3'!C6="","",'Tarefa 3'!C6) | C8: =IF('Tarefa 3'!C18="","",'Tarefa 3'!C18) | D8: =IF('Tarefa 3'!C21="","",'Tarefa 3'!C21) | E8: =IF('Tarefa 3'!C31="","",'Tarefa 3'!C31) | F8: =IF('Tarefa 3'!C32="","",'Tarefa 3'!C32) | G8: =IF('Tarefa 3'!C27="","",'Tarefa 3'!C27)
B9: =IF('Tarefa 4'!C6="","",'Tarefa 4'!C6) | C9: =IF('Tarefa 4'!C18="","",'Tarefa 4'!C18) | D9: =IF('Tarefa 4'!C21="","",'Tarefa 4'!C21) | E9: =IF('Tarefa 4'!C31="","",'Tarefa 4'!C31) | F9: =IF('Tarefa 4'!C32="","",'Tarefa 4'!C32) | G9: =IF('Tarefa 4'!C27="","",'Tarefa 4'!C27)
B10: =IF('Tarefa 5'!C6="","",'Tarefa 5'!C6) | C10: =IF('Tarefa 5'!C18="","",'Tarefa 5'!C18) | D10: =IF('Tarefa 5'!C21="","",'Tarefa 5'!C21) | E10: =IF('Tarefa 5'!C31="","",'Tarefa 5'!C31) | F10: =IF('Tarefa 5'!C32="","",'Tarefa 5'!C32) | G10: =IF('Tarefa 5'!C27="","",'Tarefa 5'!C27)
B11: Total | D11: =SUM(D6:D10) | E11: =SUM(E6:E10)
B13: Se criarem novas abas de tarefa, elas não entram aqui automaticamente — sem problema, eu considero todas na análise.
